xfin/__init__.py
xfin/main.py
xfin-1.0.2.dist-info/METADATA
xfin-1.0.2.dist-info/WHEEL
xfin-1.0.2.dist-info/entry_points.txt
xfin-1.0.2.dist-info/top_level.txt
xfin-1.0.2.dist-info/RECORD
